pado/__init__.py
pado/light.py
pado/material.py
pado/math.py
pado/optical_element.py
pado/propagator.py
pado_optics-1.0.1.dist-info/licenses/LICENSE
pado_optics-1.0.1.dist-info/METADATA
pado_optics-1.0.1.dist-info/WHEEL
pado_optics-1.0.1.dist-info/top_level.txt
pado_optics-1.0.1.dist-info/RECORD
