Metadata-Version: 2.4
Name: pado-optics
Version: 1.0.1
Summary: Pytorch Automatic Differentiable Optics
Author: Yujin Jeon, Seung-Woo Yoon, Eunsue Choi, Gawoon Ban, Hyunmo Kang
Author-email: Seung-Hwan Baek <shwbaek@postech.ac.kr>, Dong-Ha Shin <0218sdh@gmail.com>
License: MIT
Project-URL: Homepage, https://github.com/shwbaek/pado
Project-URL: Repository, https://github.com/shwbaek/pado.git
Project-URL: Documentation, https://shwbaek.github.io/pado
Requires-Python: >=3.9
License-File: LICENSE
Requires-Dist: torch>=1.10.0
Requires-Dist: numpy>=1.16.0
Requires-Dist: matplotlib>=3.3.0
Requires-Dist: scipy>=1.0.0
Dynamic: license-file
